itly_plugin_snowplow/__init__.py
itly_plugin_snowplow/_snowplow_plugin.py
itly_plugin_snowplow-0.1.5.dist-info/WHEEL
itly_plugin_snowplow-0.1.5.dist-info/METADATA
itly_plugin_snowplow-0.1.5.dist-info/RECORD
