Metadata-Version: 2.1
Name: itly-plugin-snowplow
Version: 0.1.5
Summary: Iteratively Analytics SDK - Snowplow Plugin
License: MIT
Author: Iteratively
Requires-Python: >=3.6,<4.0
Classifier: License :: OSI Approved :: MIT License
Classifier: Programming Language :: Python :: 3
Classifier: Programming Language :: Python :: 3.6
Classifier: Programming Language :: Python :: 3.7
Classifier: Programming Language :: Python :: 3.8
Classifier: Programming Language :: Python :: 3.9
Requires-Dist: snowplow-tracker (>=0.8.4,<0.9.0)
